py_hplc/__init__.py
py_hplc/pump.py
py_hplc/pump_base.py
py_hplc/pump_error.py
py_hplc-1.0.4.dist-info/LICENSE.txt
py_hplc-1.0.4.dist-info/WHEEL
py_hplc-1.0.4.dist-info/METADATA
py_hplc-1.0.4.dist-info/RECORD
