Metadata-Version: 2.1
Name: py-hplc
Version: 1.0.4
Summary: An unoffical Python wrapper for the SSI-Teledyne Next Generation class HPLC pumps.
Home-page: https://github.com/pct-code/py-hplc
License: MIT
Author: Alex W
Author-email: alex@southsun.tech
Requires-Python: >=3.9,<4.0
Classifier: Development Status :: 4 - Beta
Classifier: License :: OSI Approved :: MIT License
Classifier: Programming Language :: Python :: 3
Classifier: Programming Language :: Python :: 3.10
Classifier: Programming Language :: Python :: 3.9
Classifier: Topic :: Scientific/Engineering
Classifier: Topic :: Scientific/Engineering :: Interface Engine/Protocol Translator
Classifier: Topic :: System :: Hardware :: Universal Serial Bus (USB)
Classifier: Topic :: Terminals :: Serial
Requires-Dist: pyserial (>=3.5,<4.0)
Project-URL: Documentation, https://py-hplc.readthedocs.io/en/latest/
Project-URL: Repository, https://github.com/pct-code/py-hplc
